OpenImages/__init__.py
OpenImages/open_imgs_downloader.py
open_images/__init__.py
open_images/downloader.py
open_imgs_downloader-1.0.7.dist-info/METADATA
open_imgs_downloader-1.0.7.dist-info/WHEEL
open_imgs_downloader-1.0.7.dist-info/top_level.txt
open_imgs_downloader-1.0.7.dist-info/RECORD
