Metadata-Version: 2.1
Name: open-imgs-downloader
Version: 1.0.7
Summary: download class images from the OpenImages datasset.
Home-page: UNKNOWN
Author: xujin.huang
Author-email: 409766147@qq.com
License: UNKNOWN
Platform: UNKNOWN
Classifier: Intended Audience :: Developers
Classifier: Natural Language :: Chinese (Simplified)
Classifier: Programming Language :: Python :: 3.6
Classifier: Programming Language :: Python :: 3.7
Classifier: Topic :: Utilities
Requires-Dist: awscli (>=1.18.61)
